django_foundation_formtags-0.1.0.dist-info/DESCRIPTION.rst
django_foundation_formtags-0.1.0.dist-info/METADATA
django_foundation_formtags-0.1.0.dist-info/RECORD
django_foundation_formtags-0.1.0.dist-info/WHEEL
django_foundation_formtags-0.1.0.dist-info/metadata.json
django_foundation_formtags-0.1.0.dist-info/top_level.txt
foundation_formtags/__init__.py
foundation_formtags/templates/foundation_formtags/form.html
foundation_formtags/templates/foundation_formtags/foundation_form_field.html
foundation_formtags/templatetags/__init__.py
foundation_formtags/templatetags/__init__.pyc
foundation_formtags/templatetags/foundation_formtags.py
foundation_formtags/templatetags/foundation_formtags.pyc
foundation_formtags/tests/__init__.py
foundation_formtags/tests/__init__.pyc
foundation_formtags/tests/forms.py
foundation_formtags/tests/forms.pyc
foundation_formtags/tests/tests.py
foundation_formtags/tests/tests.pyc
