Metadata-Version: 1.1
Name: django-foundation-formtags
Version: 0.1.0
Summary: Templatetags to add Zurb Foundation support to Django Forms
Home-page: https://github.com/chrisdev/django-foundation-formtags
Author: Christopher Clarke
Author-email: cclarke@chrisdev.com
License: BSD
Keywords: foundation_formtags
Platform: UNKNOWN
Classifier: Development Status :: 2 - Pre-Alpha
Classifier: Intended Audience :: Developers
Classifier: License :: OSI Approved :: BSD License
Classifier: Natural Language :: English
Classifier: Programming Language :: Python :: 2
Classifier: Programming Language :: Python :: 2.6
Classifier: Programming Language :: Python :: 2.7
Classifier: Programming Language :: Python :: 3
Classifier: Programming Language :: Python :: 3.3
Classifier: Programming Language :: Python :: 3.4
